sayhw/__init__.py
sayhw/__main__.py
sayhw-0.1.2.dist-info/METADATA
sayhw-0.1.2.dist-info/WHEEL
sayhw-0.1.2.dist-info/entry_points.txt
sayhw-0.1.2.dist-info/top_level.txt
sayhw-0.1.2.dist-info/RECORD
